kegg_viewer/__init__.py
kegg_viewer/banner.txt
kegg_viewer/bin/__init__.py
kegg_viewer/bin/main.py
kegg_viewer/util/__init__.py
kegg_viewer/util/keggrest.py
kegg_viewer/util/png.py
kegg_viewer/util/svg.py
kegg_viewer/version/__init__.py
kegg_viewer/version/version.py
kegg_viewer-1.0.6.dist-info/METADATA
kegg_viewer-1.0.6.dist-info/WHEEL
kegg_viewer-1.0.6.dist-info/entry_points.txt
kegg_viewer-1.0.6.dist-info/top_level.txt
kegg_viewer-1.0.6.dist-info/RECORD
