Metadata-Version: 2.1
Name: kegg-viewer
Version: 1.0.6
Summary: View/Highlight KEGG Pathway
Home-page: https://github.com/suqingdong/kegg_viewer
Author: suqingdong
Author-email: suqingdong@novogene.com
License: BSD License
Platform: UNKNOWN
Classifier: Development Status :: 5 - Production/Stable
Classifier: Operating System :: OS Independent
Classifier: Intended Audience :: Developers
Classifier: License :: OSI Approved :: BSD License
Classifier: Programming Language :: Python
Classifier: Programming Language :: Python :: 3
Classifier: Programming Language :: Python :: 3.6
Classifier: Topic :: Software Development :: Libraries
Requires-Dist: pysvg-py3
Requires-Dist: requests
Requires-Dist: pillow
Requires-Dist: webrequests
Requires-Dist: simple-loggers
